[
  {
    "Isin": "IT0005556011",
    "Sigla": "3.85-BTP-15ST26",
    "UltimoPrezzo": 100.59,
    "RendimentoNetto": 3.18,
    "CedolaNetta": 3.35,
    "RendimentoTotale": 9.6,
    "EmissioneScadenza": "17/07/202315/09/2026",
    "AnniResidui": 3.03,
    "CedolaLorda": 3.85,
    "CreditoDimposta": 0.07,
    "updatedAt": "2023-09-05 09:13:28",
    "createdAt": "2023-09-05 09:13:28"
  },
  {
    "Isin": "IT0005556011",
    "Sigla": "3.85-BTP-15ST26",
    "UltimoPrezzo": 100.63,
    "RendimentoNetto": 3.17,
    "CedolaNetta": 3.35,
    "RendimentoTotale": 9.6,
    "EmissioneScadenza": "17/07/202315/09/2026",
    "AnniResidui": 3.03,
    "CedolaLorda": 3.85,
    "CreditoDimposta": 0.08,
    "updatedAt": "2023-09-06 07:08:37",
    "createdAt": "2023-09-06 07:08:37"
  },
  {
    "id": 3,
    "Isin": "IT0005556011",
    "Sigla": "3.85-BTP-15ST26",
    "UltimoPrezzo": 100.35,
    "RendimentoNetto": 3.26,
    "CedolaNetta": 3.36,
    "RendimentoTotale": 9.8,
    "EmissioneScadenza": "17/07/202315/09/2026",
    "AnniResidui": 3.02,
    "CedolaLorda": 3.85,
    "CreditoDimposta": 0.04,
    "updatedAt": "2023-09-07T07:45:13.670Z",
    "createdAt": "2023-09-07T07:45:13.670Z"
  },
  {
    "id": 4,
    "Isin": "IT0005556011",
    "Sigla": "3.85-BTP-15ST26",
    "UltimoPrezzo": 100.48,
    "RendimentoNetto": 3.21,
    "CedolaNetta": 3.35,
    "RendimentoTotale": 9.7,
    "EmissioneScadenza": "17/07/202315/09/2026",
    "AnniResidui": 3.02,
    "CedolaLorda": 3.85,
    "CreditoDimposta": 0.06,
    "updatedAt": "2023-09-08T14:28:42.107Z",
    "createdAt": "2023-09-08T14:28:42.107Z"
  },
  {
    "id": 5,
    "Isin": "IT0005556011",
    "Sigla": "3.85-BTP-15ST26",
    "UltimoPrezzo": 100.47,
    "RendimentoNetto": 3.22,
    "CedolaNetta": 3.35,
    "RendimentoTotale": 9.7,
    "EmissioneScadenza": "17/07/202315/09/2026",
    "AnniResidui": 3.02,
    "CedolaLorda": 3.85,
    "CreditoDimposta": 0.06,
    "updatedAt": "2023-09-09T08:18:11.631Z",
    "createdAt": "2023-09-09T08:18:11.631Z"
  },
  {
    "id": 6,
    "Isin": "IT0005556011",
    "Sigla": "3.85-BTP-15ST26",
    "UltimoPrezzo": 100.47,
    "RendimentoNetto": 3.22,
    "CedolaNetta": 3.35,
    "RendimentoTotale": 9.7,
    "EmissioneScadenza": "17/07/202315/09/2026",
    "AnniResidui": 3.02,
    "CedolaLorda": 3.85,
    "CreditoDimposta": 0.06,
    "updatedAt": "2023-09-11T08:47:35.277Z",
    "createdAt": "2023-09-11T08:47:35.277Z"
  },
  {
    "id": 7,
    "Isin": "IT0005556011",
    "Sigla": "3.85-BTP-15ST26",
    "UltimoPrezzo": 100.46,
    "RendimentoNetto": 3.22,
    "CedolaNetta": 3.35,
    "RendimentoTotale": 9.7,
    "EmissioneScadenza": "17/07/202315/09/2026",
    "AnniResidui": 3.01,
    "CedolaLorda": 3.85,
    "CreditoDimposta": 0.06,
    "updatedAt": "2023-09-12T07:04:51.349Z",
    "createdAt": "2023-09-12T07:04:51.349Z"
  },
  {
    "id": 8,
    "Isin": "IT0005556011",
    "Sigla": "3.85-BTP-15ST26",
    "UltimoPrezzo": 100.13,
    "RendimentoNetto": 3.33,
    "CedolaNetta": 3.36,
    "RendimentoTotale": 10,
    "EmissioneScadenza": "17/07/202315/09/2026",
    "AnniResidui": 3,
    "CedolaLorda": 3.85,
    "CreditoDimposta": 0.02,
    "updatedAt": "2023-09-13T08:30:33.964Z",
    "createdAt": "2023-09-13T08:30:33.964Z"
  },
  {
    "id": 9,
    "Isin": "IT0005556011",
    "Sigla": "3.85-BTP-15ST26",
    "UltimoPrezzo": 100.07,
    "RendimentoNetto": 3.35,
    "CedolaNetta": 3.37,
    "RendimentoTotale": 10.1,
    "EmissioneScadenza": "17/07/202315/09/2026",
    "AnniResidui": 3,
    "CedolaLorda": 3.85,
    "CreditoDimposta": 0.01,
    "updatedAt": "2023-09-14T06:57:23.912Z",
    "createdAt": "2023-09-14T06:57:23.912Z"
  },
  {
    "id": 10,
    "Isin": "IT0005556011",
    "Sigla": "3.85-BTP-15ST26",
    "UltimoPrezzo": 100.12,
    "RendimentoNetto": 3.33,
    "CedolaNetta": 3.36,
    "RendimentoTotale": 10,
    "EmissioneScadenza": "17/07/202315/09/2026",
    "AnniResidui": 3,
    "CedolaLorda": 3.85,
    "CreditoDimposta": 0.01,
    "updatedAt": "2023-09-15T09:16:27.714Z",
    "createdAt": "2023-09-15T09:16:27.714Z"
  },
  {
    "id": 11,
    "Isin": "IT0005556011",
    "Sigla": "3.85-BTP-15ST26",
    "UltimoPrezzo": 100.13,
    "RendimentoNetto": 3.33,
    "CedolaNetta": 3.36,
    "RendimentoTotale": 10,
    "EmissioneScadenza": "17/07/202315/09/2026",
    "AnniResidui": 3,
    "CedolaLorda": 3.85,
    "CreditoDimposta": 0.02,
    "updatedAt": "2023-09-16T09:09:50.913Z",
    "createdAt": "2023-09-16T09:09:50.913Z"
  },
  {
    "id": 12,
    "Isin": "IT0005556011",
    "Sigla": "3.85-BTP-15ST26",
    "UltimoPrezzo": 100.13,
    "RendimentoNetto": 3.33,
    "CedolaNetta": 3.36,
    "RendimentoTotale": 10,
    "EmissioneScadenza": "17/07/202315/09/2026",
    "AnniResidui": 3,
    "CedolaLorda": 3.85,
    "CreditoDimposta": 0.02,
    "updatedAt": "2023-09-17T08:59:47.597Z",
    "createdAt": "2023-09-17T08:59:47.597Z"
  },
  {
    "id": 13,
    "Isin": "IT0005556011",
    "Sigla": "3.85-BTP-15ST26",
    "UltimoPrezzo": 99.98,
    "RendimentoNetto": 3.38,
    "CedolaNetta": 3.37,
    "RendimentoTotale": 10.1,
    "EmissioneScadenza": "17/07/202315/09/2026",
    "AnniResidui": 2.99,
    "CedolaLorda": 3.85,
    "CreditoDimposta": 0,
    "updatedAt": "2023-09-18T16:04:07.641Z",
    "createdAt": "2023-09-18T16:04:07.641Z"
  },
  {
    "id": 14,
    "Isin": "IT0005556011",
    "Sigla": "3.85-BTP-15ST26",
    "UltimoPrezzo": 99.93,
    "RendimentoNetto": 3.39,
    "CedolaNetta": 3.37,
    "RendimentoTotale": 10.1,
    "EmissioneScadenza": "17/07/202315/09/2026",
    "AnniResidui": 2.99,
    "CedolaLorda": 3.85,
    "CreditoDimposta": 0,
    "updatedAt": "2023-09-19T07:09:43.858Z",
    "createdAt": "2023-09-19T07:09:43.858Z"
  },
  {
    "id": 15,
    "Isin": "IT0005556011",
    "Sigla": "3.85-BTP-15ST26",
    "UltimoPrezzo": 100.01,
    "RendimentoNetto": 3.37,
    "CedolaNetta": 3.37,
    "RendimentoTotale": 10,
    "EmissioneScadenza": "17/07/202315/09/2026",
    "AnniResidui": 2.99,
    "CedolaLorda": 3.85,
    "CreditoDimposta": 0,
    "updatedAt": "2023-09-20T08:33:38.895Z",
    "createdAt": "2023-09-20T08:33:38.895Z"
  },
  {
    "id": 16,
    "Isin": "IT0005556011",
    "Sigla": "3.85-BTP-15ST26",
    "UltimoPrezzo": 99.97,
    "RendimentoNetto": 3.38,
    "CedolaNetta": 3.37,
    "RendimentoTotale": 10.1,
    "EmissioneScadenza": "17/07/202315/09/2026",
    "AnniResidui": 2.98,
    "CedolaLorda": 3.85,
    "CreditoDimposta": 0,
    "updatedAt": "2023-09-21T07:27:30.350Z",
    "createdAt": "2023-09-21T07:27:30.350Z"
  },
  {
    "id": 17,
    "Isin": "IT0005556011",
    "Sigla": "3.85-BTP-15ST26",
    "UltimoPrezzo": 100.18,
    "RendimentoNetto": 3.31,
    "CedolaNetta": 3.36,
    "RendimentoTotale": 9.9,
    "EmissioneScadenza": "17/07/202315/09/2026",
    "AnniResidui": 2.98,
    "CedolaLorda": 3.85,
    "CreditoDimposta": 0.02,
    "updatedAt": "2023-09-22T07:36:55.546Z",
    "createdAt": "2023-09-22T07:36:55.546Z"
  },
  {
    "id": 18,
    "Isin": "IT0005556011",
    "Sigla": "3.85-BTP-15ST26",
    "UltimoPrezzo": 100.24,
    "RendimentoNetto": 3.29,
    "CedolaNetta": 3.36,
    "RendimentoTotale": 9.8,
    "EmissioneScadenza": "17/07/202315/09/2026",
    "AnniResidui": 2.98,
    "CedolaLorda": 3.85,
    "CreditoDimposta": 0.03,
    "updatedAt": "2023-09-23T13:05:18.089Z",
    "createdAt": "2023-09-23T13:05:18.089Z"
  }
]